{
    "authHost": "http://laravel.test:8000",
    "authEndpoint": "/broadcasting/auth",
    "clients": [{
        "appId": "APP_ID",
        "key": "56e2bf09fb7d5839532b708fc33a5b1b"
    }],
    "database": "redis",
    "databaseConfig": {
        "redis": {
            "port": "6379",
            "host": "127.0.0.1"
        },
        "sqlite": {
            "databasePath": "/database/laravel-echo-server.sqlite"
        }
    },
    "devMode": true,
    "host": "127.0.0.1",
    "port": "6001",
    "protocol": "http",
    "secureOptions": 67108864,
    "socketio": {},
    "sslCertPath": "",
    "sslKeyPath": "",
    "sslCertChainPath": "",
    "sslPassphrase": "",
    "subscribers": {
        "http": true,
        "redis": true
    },
    "apiOriginAllow": {
        "allowCors": false,
        "allowOrigin": "",
        "allowMethods": "",
        "allowHeaders": "Origin, Content-Type, X-Auth-Token, X-Requested-With, Accept, Authorization, X-CSRF-TOKEN, X-Socket-Id"
    }
}
